README.rst
authzync.py
setup.cfg
setup.py
authzync.egg-info/PKG-INFO
authzync.egg-info/SOURCES.txt
authzync.egg-info/dependency_links.txt
authzync.egg-info/requires.txt
authzync.egg-info/top_level.txt