Metadata-Version: 1.1
Name: authzync
Version: 0.1.8
Summary: SVN AuthZ-LDAP sync tool
Home-page: https://github.com/rbw0/authzync
Author: Robert Wikman
Author-email: rbw@vault13.org
License: MIT
Download-URL: https://github.com/rbw0/authzync/tarball/0.1.8
Keywords: subversion,ldap,authz,sync
Platform: any
Classifier: Programming Language :: Python
